{
  "subject_id": "35043401",
  "电影名": "断网",
  "百度指数查询词原始": "断网",
  "百度指数查询词清洗后": "断网",
  "上映日期": "2023-03-03",
  "百度指数起始日期": "2023-02-24",
  "百度指数结束日期": "2023-03-02",
  "百度指数日值列表": [
    {
      "date": "2023-02-24",
      "value": 1315.0
    },
    {
      "date": "2023-02-25",
      "value": 1463.0
    },
    {
      "date": "2023-02-26",
      "value": 1285.0
    },
    {
      "date": "2023-02-27",
      "value": 1593.0
    },
    {
      "date": "2023-02-28",
      "value": 2430.0
    },
    {
      "date": "2023-03-01",
      "value": 2802.0
    },
    {
      "date": "2023-03-02",
      "value": 4032.0
    }
  ],
  "百度指数状态": "ok",
  "百度指数错误信息": "",
  "百度指数原始提取样本数": 7
}