{
  "subject_id": "7055665",
  "电影名": "蓝学校",
  "百度指数查询词原始": "蓝学校",
  "百度指数查询词清洗后": "蓝学校",
  "上映日期": "2011-09-02",
  "百度指数起始日期": "2011-08-26",
  "百度指数结束日期": "2011-09-01",
  "百度指数日值列表": [
    {
      "date": "2011-08-26",
      "value": 0.0
    },
    {
      "date": "2011-08-27",
      "value": 63.0
    },
    {
      "date": "2011-08-28",
      "value": 0.0
    },
    {
      "date": "2011-08-29",
      "value": 0.0
    },
    {
      "date": "2011-08-30",
      "value": 61.0
    },
    {
      "date": "2011-08-31",
      "value": 0.0
    },
    {
      "date": "2011-09-01",
      "value": 118.0
    }
  ],
  "百度指数状态": "ok",
  "百度指数错误信息": "",
  "百度指数原始提取样本数": 7
}