{
  "subject_id": "26351526",
  "电影名": "幸运是我",
  "百度指数查询词原始": "幸运是我",
  "百度指数查询词清洗后": "幸运是我",
  "上映日期": "2016-08-26",
  "百度指数起始日期": "2016-08-19",
  "百度指数结束日期": "2016-08-25",
  "百度指数日值列表": [
    {
      "date": "2016-08-19",
      "value": 7635.0
    },
    {
      "date": "2016-08-20",
      "value": 8177.0
    },
    {
      "date": "2016-08-21",
      "value": 4652.0
    },
    {
      "date": "2016-08-22",
      "value": 9808.0
    },
    {
      "date": "2016-08-23",
      "value": 10908.0
    },
    {
      "date": "2016-08-24",
      "value": 11204.0
    },
    {
      "date": "2016-08-25",
      "value": 11368.0
    }
  ],
  "百度指数状态": "ok",
  "百度指数错误信息": "",
  "百度指数原始提取样本数": 7
}