{
  "subject_id": "34943661",
  "电影名": "雪豹之虎啸军魂",
  "百度指数查询词原始": "雪豹之虎啸军魂",
  "百度指数查询词清洗后": "雪豹之虎啸军魂",
  "上映日期": "2020-05-29",
  "百度指数起始日期": "2020-05-22",
  "百度指数结束日期": "2020-05-28",
  "百度指数日值列表": [
    {
      "date": "2020-05-22",
      "value": 0.0
    },
    {
      "date": "2020-05-23",
      "value": 14816.0
    },
    {
      "date": "2020-05-24",
      "value": 7151.0
    },
    {
      "date": "2020-05-25",
      "value": 5232.0
    },
    {
      "date": "2020-05-26",
      "value": 3669.0
    },
    {
      "date": "2020-05-27",
      "value": 2542.0
    },
    {
      "date": "2020-05-28",
      "value": 2623.0
    }
  ],
  "百度指数状态": "ok",
  "百度指数错误信息": "",
  "百度指数原始提取样本数": 7
}