{
  "subject_id": "34961647",
  "电影名": "宁古塔",
  "百度指数查询词原始": "宁古塔",
  "百度指数查询词清洗后": "宁古塔",
  "上映日期": "2020-02-26",
  "百度指数起始日期": "2020-02-19",
  "百度指数结束日期": "2020-02-25",
  "百度指数日值列表": [
    {
      "date": "2020-02-19",
      "value": 1220.0
    },
    {
      "date": "2020-02-20",
      "value": 3769.0
    },
    {
      "date": "2020-02-21",
      "value": 3361.0
    },
    {
      "date": "2020-02-22",
      "value": 1234.0
    },
    {
      "date": "2020-02-23",
      "value": 1257.0
    },
    {
      "date": "2020-02-24",
      "value": 1276.0
    },
    {
      "date": "2020-02-25",
      "value": 1201.0
    }
  ],
  "百度指数状态": "ok",
  "百度指数错误信息": "",
  "百度指数原始提取样本数": 7
}