{
  "subject_id": "4873490",
  "电影名": "失恋33天",
  "百度指数查询词原始": "失恋33天",
  "百度指数查询词清洗后": "失恋33天",
  "上映日期": "2011-11-08",
  "百度指数起始日期": "2011-11-01",
  "百度指数结束日期": "2011-11-07",
  "百度指数日值列表": [
    {
      "date": "2011-11-01",
      "value": 96386.0
    },
    {
      "date": "2011-11-02",
      "value": 94954.0
    },
    {
      "date": "2011-11-03",
      "value": 106338.0
    },
    {
      "date": "2011-11-04",
      "value": 133977.0
    },
    {
      "date": "2011-11-05",
      "value": 161993.0
    },
    {
      "date": "2011-11-06",
      "value": 175091.0
    },
    {
      "date": "2011-11-07",
      "value": 260128.0
    }
  ],
  "百度指数状态": "ok",
  "百度指数错误信息": "",
  "百度指数原始提取样本数": 7
}