{
  "subject_id": "10438426",
  "电影名": "浮城谜事",
  "百度指数查询词原始": "浮城谜事",
  "百度指数查询词清洗后": "浮城谜事",
  "上映日期": "2012-10-19",
  "百度指数起始日期": "2012-10-12",
  "百度指数结束日期": "2012-10-18",
  "百度指数日值列表": [
    {
      "date": "2012-10-12",
      "value": 2097.0
    },
    {
      "date": "2012-10-13",
      "value": 2418.0
    },
    {
      "date": "2012-10-14",
      "value": 2405.0
    },
    {
      "date": "2012-10-15",
      "value": 2694.0
    },
    {
      "date": "2012-10-16",
      "value": 5256.0
    },
    {
      "date": "2012-10-17",
      "value": 4021.0
    },
    {
      "date": "2012-10-18",
      "value": 5670.0
    }
  ],
  "百度指数状态": "ok",
  "百度指数错误信息": "",
  "百度指数原始提取样本数": 7
}