{
  "subject_id": "36035676",
  "电影名": "长安三万里",
  "百度指数查询词原始": "长安三万里",
  "百度指数查询词清洗后": "长安三万里",
  "上映日期": "2023-07-08",
  "百度指数起始日期": "2023-07-01",
  "百度指数结束日期": "2023-07-07",
  "百度指数日值列表": [
    {
      "date": "2023-07-01",
      "value": 20610.0
    },
    {
      "date": "2023-07-02",
      "value": 49498.0
    },
    {
      "date": "2023-07-03",
      "value": 28503.0
    },
    {
      "date": "2023-07-04",
      "value": 25842.0
    },
    {
      "date": "2023-07-05",
      "value": 24492.0
    },
    {
      "date": "2023-07-06",
      "value": 26893.0
    },
    {
      "date": "2023-07-07",
      "value": 39784.0
    }
  ],
  "百度指数状态": "ok",
  "百度指数错误信息": "",
  "百度指数原始提取样本数": 7
}