{
  "subject_id": "5343383",
  "电影名": "惊沙",
  "百度指数查询词原始": "惊沙",
  "百度指数查询词清洗后": "惊沙",
  "上映日期": "2011-03-12",
  "百度指数起始日期": "2011-03-05",
  "百度指数结束日期": "2011-03-11",
  "百度指数日值列表": [
    {
      "date": "2011-03-05",
      "value": 1060.0
    },
    {
      "date": "2011-03-06",
      "value": 1017.0
    },
    {
      "date": "2011-03-07",
      "value": 1039.0
    },
    {
      "date": "2011-03-08",
      "value": 1138.0
    },
    {
      "date": "2011-03-09",
      "value": 1910.0
    },
    {
      "date": "2011-03-10",
      "value": 4810.0
    },
    {
      "date": "2011-03-11",
      "value": 4101.0
    }
  ],
  "百度指数状态": "ok",
  "百度指数错误信息": "",
  "百度指数原始提取样本数": 7
}