{
  "subject_id": "37337369",
  "电影名": "喜羊羊与灰太狼之异国破晓",
  "百度指数查询词原始": "喜羊羊与灰太狼之异国破晓",
  "百度指数查询词清洗后": "喜羊羊与灰太狼之异国破晓",
  "上映日期": "2025-07-26",
  "百度指数起始日期": "2025-07-19",
  "百度指数结束日期": "2025-07-25",
  "百度指数日值列表": [
    {
      "date": "2025-07-19",
      "value": 3889.0
    },
    {
      "date": "2025-07-20",
      "value": 4909.0
    },
    {
      "date": "2025-07-21",
      "value": 4264.0
    },
    {
      "date": "2025-07-22",
      "value": 2998.0
    },
    {
      "date": "2025-07-23",
      "value": 3831.0
    },
    {
      "date": "2025-07-24",
      "value": 3927.0
    },
    {
      "date": "2025-07-25",
      "value": 4901.0
    }
  ],
  "百度指数状态": "ok",
  "百度指数错误信息": "",
  "百度指数原始提取样本数": 7
}