{
  "subject_id": "35474010",
  "电影名": "云霄之上",
  "百度指数查询词原始": "云霄之上",
  "百度指数查询词清洗后": "云霄之上",
  "上映日期": "2022-06-17",
  "百度指数起始日期": "2022-06-10",
  "百度指数结束日期": "2022-06-16",
  "百度指数日值列表": [
    {
      "date": "2022-06-10",
      "value": 381.0
    },
    {
      "date": "2022-06-11",
      "value": 442.0
    },
    {
      "date": "2022-06-12",
      "value": 429.0
    },
    {
      "date": "2022-06-13",
      "value": 703.0
    },
    {
      "date": "2022-06-14",
      "value": 804.0
    },
    {
      "date": "2022-06-15",
      "value": 1166.0
    },
    {
      "date": "2022-06-16",
      "value": 1265.0
    }
  ],
  "百度指数状态": "ok",
  "百度指数错误信息": "",
  "百度指数原始提取样本数": 7
}