{
  "subject_id": "35132974",
  "电影名": "我的父亲焦裕禄",
  "百度指数查询词原始": "我的父亲焦裕禄",
  "百度指数查询词清洗后": "我的父亲焦裕禄",
  "上映日期": "2021-08-06",
  "百度指数起始日期": "2021-07-30",
  "百度指数结束日期": "2021-08-05",
  "百度指数日值列表": [
    {
      "date": "2021-07-30",
      "value": 1202.0
    },
    {
      "date": "2021-07-31",
      "value": 1047.0
    },
    {
      "date": "2021-08-01",
      "value": 1021.0
    },
    {
      "date": "2021-08-02",
      "value": 1169.0
    },
    {
      "date": "2021-08-03",
      "value": 1201.0
    },
    {
      "date": "2021-08-04",
      "value": 1208.0
    },
    {
      "date": "2021-08-05",
      "value": 1310.0
    }
  ],
  "百度指数状态": "ok",
  "百度指数错误信息": "",
  "百度指数原始提取样本数": 7
}